stock_nexus_tools/__init__.py
stock_nexus_tools/event_bus.py
stock_nexus_tools-0.0.1.dist-info/METADATA
stock_nexus_tools-0.0.1.dist-info/WHEEL
stock_nexus_tools-0.0.1.dist-info/licenses/LICENSE
stock_nexus_tools-0.0.1.dist-info/RECORD
