Metadata-Version: 2.3
Name: stock_nexus_tools
Version: 0.0.1
Summary: Libraries for StockNexus Project.
Project-URL: Repository, https://github.com/DevAI-64/StockNexusTools
Author-email: StockNexus Enterprise <stock-nexus-enterprise@outlook.com>
Maintainer-email: StockNexus Enterprise <stock-nexus-enterprise@outlook.com>
License: MIT License
Classifier: License :: OSI Approved :: MIT License
Classifier: Programming Language :: Python :: 3
Requires-Python: >=3.8
Requires-Dist: pika
